vllm_router_rs.cpython-39-x86_64-linux-gnu.so
vllm_router/__init__.py
vllm_router/launch_router.py
vllm_router/mini_lb.py
vllm_router/router.py
vllm_router/router_args.py
vllm_router/version.py
vllm_router.libs/libcrypto-bfee2032.so.1.1.1k
vllm_router.libs/libssl-658e53cd.so.1.1.1k
vllm_router-0.1.9.dist-info/METADATA
vllm_router-0.1.9.dist-info/WHEEL
vllm_router-0.1.9.dist-info/entry_points.txt
vllm_router-0.1.9.dist-info/top_level.txt
vllm_router-0.1.9.dist-info/RECORD
