Metadata-Version: 2.4
Name: vllm-router
Version: 0.1.9
Summary: High-performance Rust-based load balancer for VLLM with multiple routing algorithms and prefill-decode disaggregation support
Author-email: Byron Hsu <byronhsu1230@gmail.com>
License: Apache-2.0
Classifier: Programming Language :: Python :: Implementation :: CPython
Classifier: Programming Language :: Rust
Classifier: Programming Language :: Python :: 3
Requires-Python: >=3.8
Requires-Dist: setproctitle
Requires-Dist: aiohttp
Requires-Dist: orjson
Requires-Dist: uvicorn
Requires-Dist: fastapi
Requires-Dist: requests>=2.25.0
Provides-Extra: dev
Requires-Dist: pytest>=7.0.0; extra == "dev"
Requires-Dist: pytest-asyncio>=0.21.0; extra == "dev"
Requires-Dist: pytest-cov>=4.0.0; extra == "dev"
